fgb_opram/__init__.py
fgb_opram/fuzzy_overlap.py
fgb_opram/granular_ball.py
fgb_opram/gui.py
fgb_opram/opram.py
fgb_opram/rcc8.py
fgb_opram/spatial_query_engine.py
fgb_opram/visualize.py
fgb_opram-0.1.31.dist-info/LICENSE
fgb_opram-0.1.31.dist-info/METADATA
fgb_opram-0.1.31.dist-info/WHEEL
fgb_opram-0.1.31.dist-info/entry_points.txt
fgb_opram-0.1.31.dist-info/top_level.txt
fgb_opram-0.1.31.dist-info/RECORD
