Metadata-Version: 2.2
Name: fgb-opram
Version: 0.1.31
Summary: Fuzzy Granular-Ball and OPRAm-based spatial query answering framework
Home-page: https://github.com/bongjaekwon/FGB-OPRAm-SQAUE
Author: Bongjae Kwon
Author-email: bongjae.kwon@snu.ac.kr
License: MIT
Classifier: Programming Language :: Python :: 3
Classifier: License :: OSI Approved :: MIT License
Classifier: Operating System :: OS Independent
Classifier: Topic :: Scientific/Engineering :: GIS
Classifier: Topic :: Software Development :: Libraries :: Python Modules
Requires-Python: >=3.6
License-File: LICENSE
Requires-Dist: numpy>=1.19.0
Requires-Dist: scipy>=1.5.0
Requires-Dist: matplotlib>=3.3.0
Dynamic: author
Dynamic: author-email
Dynamic: classifier
Dynamic: description
Dynamic: description-content-type
Dynamic: home-page
Dynamic: license
Dynamic: requires-dist
Dynamic: requires-python
Dynamic: summary
